schemars-0.4.0.dist-info/METADATA
schemars-0.4.0.dist-info/WHEEL
schemars-0.4.0.dist-info/license_files/LICENSE
schemars/__init__.py
schemars/_schemars.pyi
schemars/_schemars.cpython-39-powerpc64le-linux-gnu.so
schemars-0.4.0.dist-info/RECORD
