Metadata-Version: 2.1
Name: schemars
Version: 0.4.0
Classifier: Programming Language :: Rust
Classifier: Programming Language :: Python :: Implementation :: CPython
Classifier: Programming Language :: Python :: Implementation :: PyPy
License-File: LICENSE
Author-email: Michael Gendy <nagymichel13@gmail.com>
Requires-Python: >=3.7
